pywsd/__init__.py
pywsd/allwords_wsd.py
pywsd/baseline.py
pywsd/corpus.py
pywsd/cosine.py
pywsd/lesk.py
pywsd/semeval.py
pywsd/similarity.py
pywsd/stopwords.py
pywsd/tokenize.py
pywsd/utils.py
pywsd/data/signatures/signatures.pkl
pywsd-1.2.5.dist-info/LICENSE.md
pywsd-1.2.5.dist-info/METADATA
pywsd-1.2.5.dist-info/WHEEL
pywsd-1.2.5.dist-info/top_level.txt
pywsd-1.2.5.dist-info/RECORD
